{
  "schema_version": "kg_v1",
  "curriculum": "sat-act",
  "grade": "admissions",
  "sku": "sat-act",
  "subject": "sat-math",
  "chapter_id": "sat-math-polynomial",
  "title": "Polynomial Functions",
  "built_at": "2026-06-27T13:19:41.478408+00:00",
  "nodes": [
    {
      "id": "kg:sat-act:admissions:sat-math:sat-math-polynomial:chapter:sat-math-polynomial",
      "type": "chapter",
      "label": "Polynomial Functions",
      "chapter_id": "sat-math-polynomial",
      "subject": "sat-math",
      "sku": "sat-act",
      "text": "Polynomial Functions",
      "metadata": {
        "unit": "Advanced Math",
        "unit_id": "sat-math-advanced",
        "question_count": null
      },
      "sources": [
        "curriculum-json"
      ]
    },
    {
      "id": "kg:sat-act:admissions:sat-math:sat-math-polynomial:concept:sat-math-polynomial-1",
      "type": "concept",
      "label": "Polynomial operations",
      "chapter_id": "sat-math-polynomial",
      "subject": "sat-math",
      "sku": "sat-act",
      "text": "Polynomial operations",
      "metadata": {
        "skill_id": "sat-math-polynomial-1"
      },
      "sources": [
        "curriculum-json"
      ]
    },
    {
      "id": "kg:sat-act:admissions:sat-math:sat-math-polynomial:learning_objective:sat-math-polynomial-1",
      "type": "learning_objective",
      "label": "Polynomial operations",
      "chapter_id": "sat-math-polynomial",
      "subject": "sat-math",
      "sku": "sat-act",
      "text": "Demonstrate understanding of Polynomial operations.",
      "metadata": {},
      "sources": [
        "curriculum-json"
      ]
    },
    {
      "id": "kg:sat-act:admissions:sat-math:sat-math-polynomial:concept:sat-math-polynomial-2",
      "type": "concept",
      "label": "Zeros and factors",
      "chapter_id": "sat-math-polynomial",
      "subject": "sat-math",
      "sku": "sat-act",
      "text": "Zeros and factors",
      "metadata": {
        "skill_id": "sat-math-polynomial-2"
      },
      "sources": [
        "curriculum-json"
      ]
    },
    {
      "id": "kg:sat-act:admissions:sat-math:sat-math-polynomial:learning_objective:sat-math-polynomial-2",
      "type": "learning_objective",
      "label": "Zeros and factors",
      "chapter_id": "sat-math-polynomial",
      "subject": "sat-math",
      "sku": "sat-act",
      "text": "Demonstrate understanding of Zeros and factors.",
      "metadata": {},
      "sources": [
        "curriculum-json"
      ]
    },
    {
      "id": "kg:sat-act:admissions:sat-math:sat-math-polynomial:concept:core-concepts",
      "type": "concept",
      "label": "Polynomial Functions",
      "chapter_id": "sat-math-polynomial",
      "subject": "sat-math",
      "sku": "sat-act",
      "text": "Polynomial Functions",
      "metadata": {
        "fallback": true
      },
      "sources": [
        "curriculum-json"
      ]
    }
  ],
  "edges": [
    {
      "id": "edge-sat-math-polynomial-contains-sat-math-polynomial-1",
      "type": "contains",
      "from_id": "kg:sat-act:admissions:sat-math:sat-math-polynomial:chapter:sat-math-polynomial",
      "to_id": "kg:sat-act:admissions:sat-math:sat-math-polynomial:concept:sat-math-polynomial-1"
    },
    {
      "id": "edge-sat-math-polynomial-teaches-sat-math-polynomial-1",
      "type": "teaches",
      "from_id": "kg:sat-act:admissions:sat-math:sat-math-polynomial:concept:sat-math-polynomial-1",
      "to_id": "kg:sat-act:admissions:sat-math:sat-math-polynomial:learning_objective:sat-math-polynomial-1"
    },
    {
      "id": "edge-sat-math-polynomial-contains-sat-math-polynomial-2",
      "type": "contains",
      "from_id": "kg:sat-act:admissions:sat-math:sat-math-polynomial:chapter:sat-math-polynomial",
      "to_id": "kg:sat-act:admissions:sat-math:sat-math-polynomial:concept:sat-math-polynomial-2"
    },
    {
      "id": "edge-sat-math-polynomial-teaches-sat-math-polynomial-2",
      "type": "teaches",
      "from_id": "kg:sat-act:admissions:sat-math:sat-math-polynomial:concept:sat-math-polynomial-2",
      "to_id": "kg:sat-act:admissions:sat-math:sat-math-polynomial:learning_objective:sat-math-polynomial-2"
    },
    {
      "id": "edge-sat-math-polynomial-contains-core",
      "type": "contains",
      "from_id": "kg:sat-act:admissions:sat-math:sat-math-polynomial:chapter:sat-math-polynomial",
      "to_id": "kg:sat-act:admissions:sat-math:sat-math-polynomial:concept:core-concepts"
    }
  ],
  "stats": {
    "chapter": 1,
    "concept": 3,
    "learning_objective": 2,
    "edges": 5
  }
}
